{
    "display": {
        "icon": {
            "item":"minecraft:concrete",
            "data": 11
        },
        "title": "Color Control",
        "background": "minecraft:textures/blocks/hardened_clay_stained_cyan.png",
        "description": "",
        "announce_to_chat": false
    },
     "criteria": {
        "joingame": {
            "trigger": "minecraft:tick"
        }
    },
    "rewards": {
        "commands": [
            "/teleport @s -1000 31 -1000",
            "/spawnpoint @s -1000 31 -1000",
            "/tellraw @s [{\"text\":\"Welcome to \",\"color\":\"yellow\"},{\"text\":\"Color\",\"color\":\"red\",\"bold\":\"true\"},{\"text\":\" Control\",\"color\":\"blue\",\"bold\":\"true\"},{\"text\":\", a minigame by \",\"color\":\"yellow\",\"bold\":\"false\"},{\"text\":\"Sybillian!\",\"color\":\"green\"}]",
            "/gamemode 2 @s",
            "/recipe give @s *"
        ]
    }
}